mindfultensors/__init__.py
mindfultensors/gencoords.py
mindfultensors/mongoloader.py
mindfultensors/redisloader.py
mindfultensors/utils.py
mindfultensors-0.0.12.dist-info/licenses/LICENSE
mindfultensors-0.0.12.dist-info/METADATA
mindfultensors-0.0.12.dist-info/WHEEL
mindfultensors-0.0.12.dist-info/top_level.txt
mindfultensors-0.0.12.dist-info/RECORD
