Metadata-Version: 2.4
Name: mindfultensors
Version: 0.0.12
Summary: Dataloader that serves MRI images from a mogodb
Home-page: http://pypi.python.org/pypi/mindfultensors/
Author: Sergey Plis
Author-email: s.m.plis@gmail.com
License: MIT
License-File: LICENSE
Requires-Dist: numpy
Requires-Dist: scipy>=1.7
Requires-Dist: pymongo>=4.0
Requires-Dist: redis
Requires-Dist: torch
Requires-Dist: lz4
Dynamic: author
Dynamic: author-email
Dynamic: description
Dynamic: description-content-type
Dynamic: home-page
Dynamic: license
Dynamic: license-file
Dynamic: requires-dist
Dynamic: summary
